eConEXG/__init__.py
eConEXG/version.py
eConEXG/DFocus/__init__.py
eConEXG/DFocus/data_parser.py
eConEXG/DFocus/data_reader.py
eConEXG/DFocus/device_socket.py
eConEXG/eConAlpha/__init__.py
eConEXG/eConAlpha/data_parser.py
eConEXG/eConAlpha/data_reader.py
eConEXG/eConAlpha/device_socket.py
eConEXG/iFocus/__init__.py
eConEXG/iFocus/data_parser.py
eConEXG/iFocus/data_reader.py
eConEXG/iFocus/device_socket.py
eConEXG/iRecorder/__init__.py
eConEXG/iRecorder/data_parser.py
eConEXG/iRecorder/default_config.py
eConEXG/iRecorder/device.py
eConEXG/iRecorder/physical_interface/__init__.py
eConEXG/iRecorder/physical_interface/bt.py
eConEXG/iRecorder/physical_interface/com.py
eConEXG/iRecorder/physical_interface/device_socket.py
eConEXG/iRecorder/physical_interface/wifi_linux.py
eConEXG/iRecorder/physical_interface/wifi_macos.py
eConEXG/iRecorder/physical_interface/wifi_windows.py
eConEXG/iRecorder/physical_interface/bluetooth/__init__.py
eConEXG/iRecorder/physical_interface/bluetooth/btcommon.py
eConEXG/iRecorder/physical_interface/bluetooth/msbt.py
eConEXG/iRecorder/physical_interface/bluetooth/windows/_msbt.cp310-win_amd64.pyd
eConEXG/iRecorder/physical_interface/bluetooth/windows/_msbt.cp311-win_amd64.pyd
eConEXG/iRecorder/physical_interface/bluetooth/windows/_msbt.cp312-win_amd64.pyd
eConEXG/iRecorder/physical_interface/bluetooth/windows/_msbt.cp39-win_amd64.pyd
eConEXG/iSense/__init__.py
eConEXG/iSense/data_parser.py
eConEXG/iSense/dev_socket.py
eConEXG/iSense/device.py
eConEXG/iSense/libusb-1.0.dll
eConEXG/iSense/libusb-1.0.dylib
eConEXG/iSense/transform.c
eConEXG/iSense/transform.dll
eConEXG/iSense/transform.dylib
eConEXG/iSense/transform.so
eConEXG/triggerBox/__init__.py
eConEXG/triggerBox/triggerbox.py
eConEXG/utils/__init__.py
eConEXG/utils/bdfWrapper.py
eConEXG/utils/lslWrapper.py
econexg-0.2.5.dist-info/METADATA
econexg-0.2.5.dist-info/WHEEL
econexg-0.2.5.dist-info/licenses/LICENSE
econexg-0.2.5.dist-info/RECORD
