Metadata-Version: 2.3
Name: eConEXG
Version: 0.2.5
Summary: SDK for Niantong devices.
Project-URL: Homepage, https://github.com/Niantong-Intelligence/eConEXG
Project-URL: Issues, https://github.com/Niantong-Intelligence/eConEXG/issues
Project-URL: Documentation, https://niantong-intelligence.github.io/eConEXG/
Project-URL: Changelog, https://niantong-intelligence.github.io/eConEXG/changelog/
Author-email: Alex You <yoyialex@outlook.com>
Maintainer-email: Ethan Xie <xiewenxuan0000@gmail.com>
License: MIT License
Keywords: econ,eeg,emg,niantong
Classifier: License :: OSI Approved :: MIT License
Classifier: Operating System :: OS Independent
Classifier: Programming Language :: Python
Classifier: Programming Language :: Python :: 3 :: Only
Classifier: Programming Language :: Python :: 3.9
Classifier: Programming Language :: Python :: 3.10
Classifier: Programming Language :: Python :: 3.11
Classifier: Programming Language :: Python :: 3.12
Requires-Python: >=3.9
Requires-Dist: numpy
Requires-Dist: pyserial>=3.5
Provides-Extra: bdf
Requires-Dist: pyedflib>=0.1.38; extra == 'bdf'
Provides-Extra: lsl
Requires-Dist: pylsl>=1.16.2; extra == 'lsl'
Provides-Extra: usb
Requires-Dist: pyusb>=1.2.1; extra == 'usb'
Provides-Extra: wifi
Requires-Dist: comtypes; (platform_system == 'Windows') and extra == 'wifi'
Requires-Dist: netifaces2; (platform_system == 'Linux') and extra == 'wifi'
Requires-Dist: netifaces; (platform_system == 'Darwin') and extra == 'wifi'
Requires-Dist: netifaces; (platform_system == 'Windows') and extra == 'wifi'
Requires-Dist: pyobjc-framework-corelocation; (platform_system == 'Darwin') and extra == 'wifi'
Requires-Dist: pyobjc-framework-corewlan; (platform_system == 'Darwin') and extra == 'wifi'
Requires-Dist: pywifi>=1.1.12; (platform_system == 'Windows') and extra == 'wifi'
